{
  "nid": 1,
  "tag": "div",
  "rect": {
    "x": 0,
    "y": 0,
    "w": 1440,
    "h": 2000
  },
  "layerType": "frame",
  "layerName": "Web首页根容器",
  "layerDescription": "Web首页根容器",
  "style": {
    "backgroundColor": "rgb(255,255,255)"
  },
  "children": [
    {
      "nid": 2,
      "tag": "header",
      "rect": {
        "x": 0,
        "y": 0,
        "w": 1440,
        "h": 64,
        "fixed": true
      },
      "layerType": "frame",
      "layerName": "顶部导航栏",
      "layerDescription": "顶部导航栏",
      "style": {
        "backgroundColor": "rgb(255,255,255)",
        "boxShadow": "0px 1px 0px rgba(0,0,0,0.08)",
        "display": "flex",
        "alignItems": "center"
      },
      "children": [
        {
          "nid": 3,
          "tag": "img",
          "rect": {
            "x": 40,
            "y": 16,
            "w": 120,
            "h": 32
          },
          "layerType": "image",
          "layerName": "Logo图片",
          "layerDescription": "Logo图片",
          "style": {}
        },
        {
          "nid": 4,
          "tag": "span",
          "rect": {
            "x": 500,
            "y": 20,
            "w": 60,
            "h": 24
          },
          "layerType": "text",
          "layerName": "导航链接-首页",
          "layerDescription": "导航链接-首页",
          "style": {
            "fontSize": "14px"
          },
          "text": "首页"
        },
        {
          "nid": 5,
          "tag": "span",
          "rect": {
            "x": 592,
            "y": 20,
            "w": 60,
            "h": 24
          },
          "layerType": "text",
          "layerName": "导航链接-产品",
          "layerDescription": "导航链接-产品",
          "style": {
            "fontSize": "14px"
          },
          "text": "产品"
        },
        {
          "nid": 6,
          "tag": "span",
          "rect": {
            "x": 684,
            "y": 20,
            "w": 60,
            "h": 24
          },
          "layerType": "text",
          "layerName": "导航链接-方案",
          "layerDescription": "导航链接-方案",
          "style": {
            "fontSize": "14px"
          },
          "text": "方案"
        },
        {
          "nid": 7,
          "tag": "span",
          "rect": {
            "x": 776,
            "y": 20,
            "w": 60,
            "h": 24
          },
          "layerType": "text",
          "layerName": "导航链接-定价",
          "layerDescription": "导航链接-定价",
          "style": {
            "fontSize": "14px"
          },
          "text": "定价"
        },
        {
          "nid": 8,
          "tag": "span",
          "rect": {
            "x": 868,
            "y": 20,
            "w": 60,
            "h": 24
          },
          "layerType": "text",
          "layerName": "导航链接-文档",
          "layerDescription": "导航链接-文档",
          "style": {
            "fontSize": "14px"
          },
          "text": "文档"
        },
        {
          "nid": 9,
          "tag": "div",
          "rect": {
            "x": 1100,
            "y": 16,
            "w": 200,
            "h": 32
          },
          "layerType": "component",
          "layerName": "顶部搜索框",
          "layerDescription": "顶部搜索框",
          "style": {
            "borderRadius": "6px",
            "backgroundColor": "rgb(246,246,246)"
          }
        },
        {
          "nid": 10,
          "tag": "span",
          "rect": {
            "x": 1316,
            "y": 20,
            "w": 24,
            "h": 24
          },
          "layerType": "icon",
          "layerName": "消息通知图标 24×24 细线",
          "layerDescription": "消息通知图标 24×24 细线",
          "style": {}
        },
        {
          "nid": 11,
          "tag": "div",
          "rect": {
            "x": 1360,
            "y": 12,
            "w": 40,
            "h": 40
          },
          "layerType": "component",
          "layerName": "用户头像",
          "layerDescription": "用户头像",
          "style": {
            "borderRadius": "50%"
          }
        }
      ]
    },
    {
      "nid": 12,
      "tag": "section",
      "rect": {
        "x": 0,
        "y": 64,
        "w": 1440,
        "h": 480
      },
      "layerType": "frame",
      "layerName": "Hero区域",
      "layerDescription": "Hero区域",
      "style": {
        "backgroundColor": "rgb(248,250,252)"
      },
      "children": [
        {
          "nid": 13,
          "tag": "img",
          "rect": {
            "x": 680,
            "y": 64,
            "w": 760,
            "h": 480
          },
          "layerType": "image",
          "layerName": "Hero背景插图",
          "layerDescription": "Hero背景插图",
          "style": {}
        },
        {
          "nid": 14,
          "tag": "span",
          "rect": {
            "x": 120,
            "y": 140,
            "w": 88,
            "h": 28
          },
          "layerType": "component",
          "layerName": "新功能角标",
          "layerDescription": "新功能角标",
          "style": {
            "backgroundColor": "rgb(239,246,255)",
            "borderRadius": "14px",
            "fontSize": "12px"
          },
          "text": "✨ 新功能"
        },
        {
          "nid": 15,
          "tag": "h1",
          "rect": {
            "x": 120,
            "y": 184,
            "w": 540,
            "h": 96
          },
          "layerType": "text",
          "layerName": "Hero主标题",
          "layerDescription": "Hero主标题",
          "style": {
            "fontSize": "48px",
            "fontWeight": "700",
            "lineHeight": "1.2"
          },
          "text": "打造更好的数字协作体验"
        },
        {
          "nid": 16,
          "tag": "p",
          "rect": {
            "x": 120,
            "y": 296,
            "w": 480,
            "h": 60
          },
          "layerType": "text",
          "layerName": "Hero副标题",
          "layerDescription": "Hero副标题",
          "style": {
            "fontSize": "18px",
            "color": "rgb(100,116,139)"
          },
          "text": "专业的设计工具平台，帮助团队高效协作，提升设计效率与质量。"
        },
        {
          "nid": 17,
          "tag": "button",
          "rect": {
            "x": 120,
            "y": 376,
            "w": 160,
            "h": 52
          },
          "layerType": "component",
          "layerName": "主CTA按钮-免费开始",
          "layerDescription": "主CTA按钮-免费开始",
          "style": {
            "backgroundColor": "rgb(59,130,246)",
            "borderRadius": "8px",
            "fontSize": "16px",
            "fontWeight": "600",
            "color": "rgb(255,255,255)"
          },
          "text": "免费开始"
        },
        {
          "nid": 18,
          "tag": "button",
          "rect": {
            "x": 292,
            "y": 376,
            "w": 148,
            "h": 52
          },
          "layerType": "component",
          "layerName": "次CTA按钮-了解更多",
          "layerDescription": "次CTA按钮-了解更多",
          "style": {
            "borderRadius": "8px",
            "fontSize": "16px",
            "border": "1px solid rgb(203,213,225)"
          },
          "text": "了解更多"
        }
      ]
    },
    {
      "nid": 19,
      "tag": "section",
      "rect": {
        "x": 0,
        "y": 544,
        "w": 1440,
        "h": 520
      },
      "layerType": "frame",
      "layerName": "核心功能区",
      "layerDescription": "核心功能区",
      "style": {
        "backgroundColor": "rgb(255,255,255)"
      },
      "children": [
        {
          "nid": 20,
          "tag": "span",
          "rect": {
            "x": 660,
            "y": 576,
            "w": 120,
            "h": 28
          },
          "layerType": "component",
          "layerName": "功能分区标签",
          "layerDescription": "功能分区标签",
          "style": {
            "backgroundColor": "rgb(239,246,255)",
            "borderRadius": "14px",
            "fontSize": "12px"
          },
          "text": "核心功能"
        },
        {
          "nid": 21,
          "tag": "h2",
          "rect": {
            "x": 470,
            "y": 620,
            "w": 500,
            "h": 48
          },
          "layerType": "text",
          "layerName": "功能区主标题",
          "layerDescription": "功能区主标题",
          "style": {
            "fontSize": "32px",
            "fontWeight": "700",
            "textAlign": "center"
          },
          "text": "为什么选择我们的平台"
        },
        {
          "nid": 22,
          "tag": "p",
          "rect": {
            "x": 380,
            "y": 684,
            "w": 680,
            "h": 40
          },
          "layerType": "text",
          "layerName": "功能区副标题",
          "layerDescription": "功能区副标题",
          "style": {
            "fontSize": "16px",
            "color": "rgb(100,116,139)",
            "textAlign": "center"
          },
          "text": "我们提供全套专业设计协作工具，满足团队从设计到交付的全流程需求"
        },
        {
          "nid": 23,
          "tag": "div",
          "rect": {
            "x": 120,
            "y": 752,
            "w": 360,
            "h": 272
          },
          "layerType": "frame",
          "layerName": "功能卡片-智能设计",
          "layerDescription": "功能卡片-智能设计",
          "style": {
            "backgroundColor": "rgb(248,250,252)",
            "borderRadius": "12px"
          },
          "children": [
            {
              "nid": 24,
              "tag": "span",
              "rect": {
                "x": 152,
                "y": 784,
                "w": 48,
                "h": 48
              },
              "layerType": "icon",
              "layerName": "智能设计图标 48×48 细线",
              "layerDescription": "智能设计图标 48×48 细线",
              "style": {}
            },
            {
              "nid": 25,
              "tag": "h3",
              "rect": {
                "x": 152,
                "y": 848,
                "w": 296,
                "h": 28
              },
              "layerType": "text",
              "layerName": "卡片标题-智能设计辅助",
              "layerDescription": "卡片标题-智能设计辅助",
              "style": {
                "fontSize": "18px",
                "fontWeight": "600"
              },
              "text": "智能设计辅助"
            },
            {
              "nid": 26,
              "tag": "p",
              "rect": {
                "x": 152,
                "y": 892,
                "w": 296,
                "h": 72
              },
              "layerType": "text",
              "layerName": "卡片描述-智能设计",
              "layerDescription": "卡片描述-智能设计",
              "style": {
                "fontSize": "14px",
                "color": "rgb(100,116,139)"
              },
              "text": "AI驱动的设计建议，自动布局优化，让创意落地更快更准。"
            }
          ]
        },
        {
          "nid": 27,
          "tag": "div",
          "rect": {
            "x": 540,
            "y": 752,
            "w": 360,
            "h": 272
          },
          "layerType": "frame",
          "layerName": "功能卡片-团队协作",
          "layerDescription": "功能卡片-团队协作",
          "style": {
            "backgroundColor": "rgb(248,250,252)",
            "borderRadius": "12px"
          },
          "children": [
            {
              "nid": 28,
              "tag": "span",
              "rect": {
                "x": 572,
                "y": 784,
                "w": 48,
                "h": 48
              },
              "layerType": "icon",
              "layerName": "协作图标 48×48 细线",
              "layerDescription": "协作图标 48×48 细线",
              "style": {}
            },
            {
              "nid": 29,
              "tag": "h3",
              "rect": {
                "x": 572,
                "y": 848,
                "w": 296,
                "h": 28
              },
              "layerType": "text",
              "layerName": "卡片标题-实时团队协作",
              "layerDescription": "卡片标题-实时团队协作",
              "style": {
                "fontSize": "18px",
                "fontWeight": "600"
              },
              "text": "实时团队协作"
            },
            {
              "nid": 30,
              "tag": "p",
              "rect": {
                "x": 572,
                "y": 892,
                "w": 296,
                "h": 72
              },
              "layerType": "text",
              "layerName": "卡片描述-团队协作",
              "layerDescription": "卡片描述-团队协作",
              "style": {
                "fontSize": "14px",
                "color": "rgb(100,116,139)"
              },
              "text": "多人实时协同编辑，版本历史追踪，评论与标注一体化。"
            }
          ]
        },
        {
          "nid": 31,
          "tag": "div",
          "rect": {
            "x": 960,
            "y": 752,
            "w": 360,
            "h": 272
          },
          "layerType": "frame",
          "layerName": "功能卡片-数据洞察",
          "layerDescription": "功能卡片-数据洞察",
          "style": {
            "backgroundColor": "rgb(248,250,252)",
            "borderRadius": "12px"
          },
          "children": [
            {
              "nid": 32,
              "tag": "span",
              "rect": {
                "x": 992,
                "y": 784,
                "w": 48,
                "h": 48
              },
              "layerType": "icon",
              "layerName": "数据图标 48×48 细线",
              "layerDescription": "数据图标 48×48 细线",
              "style": {}
            },
            {
              "nid": 33,
              "tag": "h3",
              "rect": {
                "x": 992,
                "y": 848,
                "w": 296,
                "h": 28
              },
              "layerType": "text",
              "layerName": "卡片标题-数据分析洞察",
              "layerDescription": "卡片标题-数据分析洞察",
              "style": {
                "fontSize": "18px",
                "fontWeight": "600"
              },
              "text": "数据分析洞察"
            },
            {
              "nid": 34,
              "tag": "p",
              "rect": {
                "x": 992,
                "y": 892,
                "w": 296,
                "h": 72
              },
              "layerType": "text",
              "layerName": "卡片描述-数据洞察",
              "layerDescription": "卡片描述-数据洞察",
              "style": {
                "fontSize": "14px",
                "color": "rgb(100,116,139)"
              },
              "text": "用户行为分析，设计效果追踪，数据驱动的设计决策支持。"
            }
          ]
        }
      ]
    },
    {
      "nid": 35,
      "tag": "section",
      "rect": {
        "x": 0,
        "y": 1064,
        "w": 1440,
        "h": 480
      },
      "layerType": "frame",
      "layerName": "图文内容区",
      "layerDescription": "图文内容区",
      "style": {
        "backgroundColor": "rgb(248,250,252)"
      },
      "children": [
        {
          "nid": 36,
          "tag": "img",
          "rect": {
            "x": 120,
            "y": 1096,
            "w": 560,
            "h": 360
          },
          "layerType": "image",
          "layerName": "产品截图",
          "layerDescription": "产品截图",
          "style": {
            "borderRadius": "12px"
          }
        },
        {
          "nid": 37,
          "tag": "h2",
          "rect": {
            "x": 760,
            "y": 1096,
            "w": 520,
            "h": 52
          },
          "layerType": "text",
          "layerName": "内容区标题",
          "layerDescription": "内容区标题",
          "style": {
            "fontSize": "32px",
            "fontWeight": "700"
          },
          "text": "深度定制你的工作流"
        },
        {
          "nid": 38,
          "tag": "p",
          "rect": {
            "x": 760,
            "y": 1164,
            "w": 520,
            "h": 72
          },
          "layerType": "text",
          "layerName": "内容区描述",
          "layerDescription": "内容区描述",
          "style": {
            "fontSize": "16px",
            "color": "rgb(100,116,139)"
          },
          "text": "从快捷键到插件系统，从云端同步到企业安全，每一个细节都为专业团队量身打造。"
        },
        {
          "nid": 39,
          "tag": "div",
          "rect": {
            "x": 760,
            "y": 1252,
            "w": 520,
            "h": 256
          },
          "layerType": "frame",
          "layerName": "特性列表",
          "layerDescription": "特性列表",
          "style": {},
          "children": [
            {
              "nid": 40,
              "tag": "div",
              "rect": {
                "x": 760,
                "y": 1252,
                "w": 520,
                "h": 56
              },
              "layerType": "frame",
              "layerName": "特性列表项1",
              "layerDescription": "特性列表项1",
              "style": {},
              "children": [
                {
                  "nid": 41,
                  "tag": "span",
                  "rect": {
                    "x": 760,
                    "y": 1268,
                    "w": 24,
                    "h": 24
                  },
                  "layerType": "icon",
                  "layerName": "勾选图标 24×24 细线",
                  "layerDescription": "勾选图标 24×24 细线",
                  "style": {}
                },
                {
                  "nid": 42,
                  "tag": "span",
                  "rect": {
                    "x": 800,
                    "y": 1268,
                    "w": 440,
                    "h": 24
                  },
                  "layerType": "text",
                  "layerName": "特性描述1",
                  "layerDescription": "特性描述1",
                  "style": {
                    "fontSize": "15px"
                  },
                  "text": "自定义快捷键和工具栏布局"
                }
              ]
            },
            {
              "nid": 43,
              "tag": "hr",
              "rect": {
                "x": 760,
                "y": 1308,
                "w": 520,
                "h": 1
              },
              "layerType": "frame",
              "layerName": "特性列表分割线1",
              "layerDescription": "特性列表分割线1",
              "style": {}
            },
            {
              "nid": 44,
              "tag": "div",
              "rect": {
                "x": 760,
                "y": 1309,
                "w": 520,
                "h": 56
              },
              "layerType": "frame",
              "layerName": "特性列表项2",
              "layerDescription": "特性列表项2",
              "style": {},
              "children": [
                {
                  "nid": 45,
                  "tag": "span",
                  "rect": {
                    "x": 760,
                    "y": 1325,
                    "w": 24,
                    "h": 24
                  },
                  "layerType": "icon",
                  "layerName": "勾选图标 24×24 细线",
                  "layerDescription": "勾选图标 24×24 细线",
                  "style": {}
                },
                {
                  "nid": 46,
                  "tag": "span",
                  "rect": {
                    "x": 800,
                    "y": 1325,
                    "w": 440,
                    "h": 24
                  },
                  "layerType": "text",
                  "layerName": "特性描述2",
                  "layerDescription": "特性描述2",
                  "style": {
                    "fontSize": "15px"
                  },
                  "text": "丰富的插件生态系统与开放API"
                }
              ]
            },
            {
              "nid": 47,
              "tag": "hr",
              "rect": {
                "x": 760,
                "y": 1365,
                "w": 520,
                "h": 1
              },
              "layerType": "frame",
              "layerName": "特性列表分割线2",
              "layerDescription": "特性列表分割线2",
              "style": {}
            },
            {
              "nid": 48,
              "tag": "div",
              "rect": {
                "x": 760,
                "y": 1366,
                "w": 520,
                "h": 56
              },
              "layerType": "frame",
              "layerName": "特性列表项3",
              "layerDescription": "特性列表项3",
              "style": {},
              "children": [
                {
                  "nid": 49,
                  "tag": "span",
                  "rect": {
                    "x": 760,
                    "y": 1382,
                    "w": 24,
                    "h": 24
                  },
                  "layerType": "icon",
                  "layerName": "勾选图标 24×24 细线",
                  "layerDescription": "勾选图标 24×24 细线",
                  "style": {}
                },
                {
                  "nid": 50,
                  "tag": "span",
                  "rect": {
                    "x": 800,
                    "y": 1382,
                    "w": 440,
                    "h": 24
                  },
                  "layerType": "text",
                  "layerName": "特性描述3",
                  "layerDescription": "特性描述3",
                  "style": {
                    "fontSize": "15px"
                  },
                  "text": "多平台无缝云端同步"
                }
              ]
            },
            {
              "nid": 51,
              "tag": "hr",
              "rect": {
                "x": 760,
                "y": 1422,
                "w": 520,
                "h": 1
              },
              "layerType": "frame",
              "layerName": "特性列表分割线3",
              "layerDescription": "特性列表分割线3",
              "style": {}
            },
            {
              "nid": 52,
              "tag": "div",
              "rect": {
                "x": 760,
                "y": 1423,
                "w": 520,
                "h": 56
              },
              "layerType": "frame",
              "layerName": "特性列表项4",
              "layerDescription": "特性列表项4",
              "style": {},
              "children": [
                {
                  "nid": 53,
                  "tag": "span",
                  "rect": {
                    "x": 760,
                    "y": 1439,
                    "w": 24,
                    "h": 24
                  },
                  "layerType": "icon",
                  "layerName": "勾选图标 24×24 细线",
                  "layerDescription": "勾选图标 24×24 细线",
                  "style": {}
                },
                {
                  "nid": 54,
                  "tag": "span",
                  "rect": {
                    "x": 800,
                    "y": 1439,
                    "w": 440,
                    "h": 24
                  },
                  "layerType": "text",
                  "layerName": "特性描述4",
                  "layerDescription": "特性描述4",
                  "style": {
                    "fontSize": "15px"
                  },
                  "text": "企业级安全与合规认证"
                }
              ]
            }
          ]
        }
      ]
    },
    {
      "nid": 55,
      "tag": "section",
      "rect": {
        "x": 0,
        "y": 1544,
        "w": 1440,
        "h": 160
      },
      "layerType": "frame",
      "layerName": "数据统计横幅",
      "layerDescription": "数据统计横幅",
      "style": {
        "backgroundColor": "rgb(59,130,246)"
      },
      "children": [
        {
          "nid": 56,
          "tag": "div",
          "rect": {
            "x": 160,
            "y": 1576,
            "w": 260,
            "h": 96
          },
          "layerType": "frame",
          "layerName": "统计数据1-注册用户",
          "layerDescription": "统计数据1-注册用户",
          "style": {},
          "children": [
            {
              "nid": 57,
              "tag": "span",
              "rect": {
                "x": 160,
                "y": 1576,
                "w": 260,
                "h": 48
              },
              "layerType": "text",
              "layerName": "统计数字-500万+",
              "layerDescription": "统计数字-500万+",
              "style": {
                "fontSize": "36px",
                "fontWeight": "700",
                "color": "rgb(255,255,255)",
                "textAlign": "center"
              },
              "text": "500万+"
            },
            {
              "nid": 58,
              "tag": "span",
              "rect": {
                "x": 160,
                "y": 1632,
                "w": 260,
                "h": 24
              },
              "layerType": "text",
              "layerName": "统计标签-注册用户",
              "layerDescription": "统计标签-注册用户",
              "style": {
                "fontSize": "14px",
                "color": "rgb(219,234,254)",
                "textAlign": "center"
              },
              "text": "注册用户"
            }
          ]
        },
        {
          "nid": 59,
          "tag": "div",
          "rect": {
            "x": 590,
            "y": 1576,
            "w": 260,
            "h": 96
          },
          "layerType": "frame",
          "layerName": "统计数据2-企业客户",
          "layerDescription": "统计数据2-企业客户",
          "style": {},
          "children": [
            {
              "nid": 60,
              "tag": "span",
              "rect": {
                "x": 590,
                "y": 1576,
                "w": 260,
                "h": 48
              },
              "layerType": "text",
              "layerName": "统计数字-10万+",
              "layerDescription": "统计数字-10万+",
              "style": {
                "fontSize": "36px",
                "fontWeight": "700",
                "color": "rgb(255,255,255)",
                "textAlign": "center"
              },
              "text": "10万+"
            },
            {
              "nid": 61,
              "tag": "span",
              "rect": {
                "x": 590,
                "y": 1632,
                "w": 260,
                "h": 24
              },
              "layerType": "text",
              "layerName": "统计标签-企业客户",
              "layerDescription": "统计标签-企业客户",
              "style": {
                "fontSize": "14px",
                "color": "rgb(219,234,254)",
                "textAlign": "center"
              },
              "text": "企业客户"
            }
          ]
        },
        {
          "nid": 62,
          "tag": "div",
          "rect": {
            "x": 1020,
            "y": 1576,
            "w": 260,
            "h": 96
          },
          "layerType": "frame",
          "layerName": "统计数据3-服务可用率",
          "layerDescription": "统计数据3-服务可用率",
          "style": {},
          "children": [
            {
              "nid": 63,
              "tag": "span",
              "rect": {
                "x": 1020,
                "y": 1576,
                "w": 260,
                "h": 48
              },
              "layerType": "text",
              "layerName": "统计数字-99.9%",
              "layerDescription": "统计数字-99.9%",
              "style": {
                "fontSize": "36px",
                "fontWeight": "700",
                "color": "rgb(255,255,255)",
                "textAlign": "center"
              },
              "text": "99.9%"
            },
            {
              "nid": 64,
              "tag": "span",
              "rect": {
                "x": 1020,
                "y": 1632,
                "w": 260,
                "h": 24
              },
              "layerType": "text",
              "layerName": "统计标签-服务可用率",
              "layerDescription": "统计标签-服务可用率",
              "style": {
                "fontSize": "14px",
                "color": "rgb(219,234,254)",
                "textAlign": "center"
              },
              "text": "服务可用率"
            }
          ]
        }
      ]
    },
    {
      "nid": 65,
      "tag": "footer",
      "rect": {
        "x": 0,
        "y": 1704,
        "w": 1440,
        "h": 296
      },
      "layerType": "frame",
      "layerName": "页脚",
      "layerDescription": "页脚",
      "style": {
        "backgroundColor": "rgb(15,23,42)"
      },
      "children": [
        {
          "nid": 66,
          "tag": "div",
          "rect": {
            "x": 120,
            "y": 1736,
            "w": 280,
            "h": 180
          },
          "layerType": "frame",
          "layerName": "品牌信息列",
          "layerDescription": "品牌信息列",
          "style": {},
          "children": [
            {
              "nid": 67,
              "tag": "img",
              "rect": {
                "x": 120,
                "y": 1736,
                "w": 120,
                "h": 32
              },
              "layerType": "image",
              "layerName": "页脚Logo",
              "layerDescription": "页脚Logo",
              "style": {}
            },
            {
              "nid": 68,
              "tag": "p",
              "rect": {
                "x": 120,
                "y": 1784,
                "w": 280,
                "h": 56
              },
              "layerType": "text",
              "layerName": "品牌描述文字",
              "layerDescription": "品牌描述文字",
              "style": {
                "fontSize": "14px",
                "color": "rgb(148,163,184)"
              },
              "text": "打造更好的数字体验，专业可靠。"
            },
            {
              "nid": 69,
              "tag": "span",
              "rect": {
                "x": 120,
                "y": 1856,
                "w": 24,
                "h": 24
              },
              "layerType": "icon",
              "layerName": "社交图标-微博 24×24 细线",
              "layerDescription": "社交图标-微博 24×24 细线",
              "style": {}
            },
            {
              "nid": 70,
              "tag": "span",
              "rect": {
                "x": 152,
                "y": 1856,
                "w": 24,
                "h": 24
              },
              "layerType": "icon",
              "layerName": "社交图标-微信 24×24 细线",
              "layerDescription": "社交图标-微信 24×24 细线",
              "style": {}
            },
            {
              "nid": 71,
              "tag": "span",
              "rect": {
                "x": 184,
                "y": 1856,
                "w": 24,
                "h": 24
              },
              "layerType": "icon",
              "layerName": "社交图标-Github 24×24 细线",
              "layerDescription": "社交图标-Github 24×24 细线",
              "style": {}
            }
          ]
        },
        {
          "nid": 72,
          "tag": "div",
          "rect": {
            "x": 520,
            "y": 1736,
            "w": 160,
            "h": 160
          },
          "layerType": "frame",
          "layerName": "产品导航列",
          "layerDescription": "产品导航列",
          "style": {},
          "children": [
            {
              "nid": 73,
              "tag": "h4",
              "rect": {
                "x": 520,
                "y": 1736,
                "w": 160,
                "h": 24
              },
              "layerType": "text",
              "layerName": "页脚列标题-产品",
              "layerDescription": "页脚列标题-产品",
              "style": {
                "fontSize": "14px",
                "fontWeight": "600",
                "color": "rgb(255,255,255)"
              },
              "text": "产品"
            },
            {
              "nid": 74,
              "tag": "span",
              "rect": {
                "x": 520,
                "y": 1776,
                "w": 160,
                "h": 20
              },
              "layerType": "text",
              "layerName": "页脚链接-功能介绍",
              "layerDescription": "页脚链接-功能介绍",
              "style": {
                "fontSize": "14px",
                "color": "rgb(148,163,184)"
              },
              "text": "功能介绍"
            },
            {
              "nid": 75,
              "tag": "span",
              "rect": {
                "x": 520,
                "y": 1808,
                "w": 160,
                "h": 20
              },
              "layerType": "text",
              "layerName": "页脚链接-定价方案",
              "layerDescription": "页脚链接-定价方案",
              "style": {
                "fontSize": "14px",
                "color": "rgb(148,163,184)"
              },
              "text": "定价方案"
            },
            {
              "nid": 76,
              "tag": "span",
              "rect": {
                "x": 520,
                "y": 1840,
                "w": 160,
                "h": 20
              },
              "layerType": "text",
              "layerName": "页脚链接-更新日志",
              "layerDescription": "页脚链接-更新日志",
              "style": {
                "fontSize": "14px",
                "color": "rgb(148,163,184)"
              },
              "text": "更新日志"
            },
            {
              "nid": 77,
              "tag": "span",
              "rect": {
                "x": 520,
                "y": 1872,
                "w": 160,
                "h": 20
              },
              "layerType": "text",
              "layerName": "页脚链接-路线图",
              "layerDescription": "页脚链接-路线图",
              "style": {
                "fontSize": "14px",
                "color": "rgb(148,163,184)"
              },
              "text": "路线图"
            }
          ]
        },
        {
          "nid": 78,
          "tag": "div",
          "rect": {
            "x": 800,
            "y": 1736,
            "w": 160,
            "h": 160
          },
          "layerType": "frame",
          "layerName": "公司导航列",
          "layerDescription": "公司导航列",
          "style": {},
          "children": [
            {
              "nid": 79,
              "tag": "h4",
              "rect": {
                "x": 800,
                "y": 1736,
                "w": 160,
                "h": 24
              },
              "layerType": "text",
              "layerName": "页脚列标题-公司",
              "layerDescription": "页脚列标题-公司",
              "style": {
                "fontSize": "14px",
                "fontWeight": "600",
                "color": "rgb(255,255,255)"
              },
              "text": "公司"
            },
            {
              "nid": 80,
              "tag": "span",
              "rect": {
                "x": 800,
                "y": 1776,
                "w": 160,
                "h": 20
              },
              "layerType": "text",
              "layerName": "页脚链接-关于我们",
              "layerDescription": "页脚链接-关于我们",
              "style": {
                "fontSize": "14px",
                "color": "rgb(148,163,184)"
              },
              "text": "关于我们"
            },
            {
              "nid": 81,
              "tag": "span",
              "rect": {
                "x": 800,
                "y": 1808,
                "w": 160,
                "h": 20
              },
              "layerType": "text",
              "layerName": "页脚链接-团队成员",
              "layerDescription": "页脚链接-团队成员",
              "style": {
                "fontSize": "14px",
                "color": "rgb(148,163,184)"
              },
              "text": "团队成员"
            },
            {
              "nid": 82,
              "tag": "span",
              "rect": {
                "x": 800,
                "y": 1840,
                "w": 160,
                "h": 20
              },
              "layerType": "text",
              "layerName": "页脚链接-加入我们",
              "layerDescription": "页脚链接-加入我们",
              "style": {
                "fontSize": "14px",
                "color": "rgb(148,163,184)"
              },
              "text": "加入我们"
            },
            {
              "nid": 83,
              "tag": "span",
              "rect": {
                "x": 800,
                "y": 1872,
                "w": 160,
                "h": 20
              },
              "layerType": "text",
              "layerName": "页脚链接-新闻中心",
              "layerDescription": "页脚链接-新闻中心",
              "style": {
                "fontSize": "14px",
                "color": "rgb(148,163,184)"
              },
              "text": "新闻中心"
            }
          ]
        },
        {
          "nid": 84,
          "tag": "div",
          "rect": {
            "x": 1080,
            "y": 1736,
            "w": 160,
            "h": 160
          },
          "layerType": "frame",
          "layerName": "支持导航列",
          "layerDescription": "支持导航列",
          "style": {},
          "children": [
            {
              "nid": 85,
              "tag": "h4",
              "rect": {
                "x": 1080,
                "y": 1736,
                "w": 160,
                "h": 24
              },
              "layerType": "text",
              "layerName": "页脚列标题-支持",
              "layerDescription": "页脚列标题-支持",
              "style": {
                "fontSize": "14px",
                "fontWeight": "600",
                "color": "rgb(255,255,255)"
              },
              "text": "支持"
            },
            {
              "nid": 86,
              "tag": "span",
              "rect": {
                "x": 1080,
                "y": 1776,
                "w": 160,
                "h": 20
              },
              "layerType": "text",
              "layerName": "页脚链接-帮助中心",
              "layerDescription": "页脚链接-帮助中心",
              "style": {
                "fontSize": "14px",
                "color": "rgb(148,163,184)"
              },
              "text": "帮助中心"
            },
            {
              "nid": 87,
              "tag": "span",
              "rect": {
                "x": 1080,
                "y": 1808,
                "w": 160,
                "h": 20
              },
              "layerType": "text",
              "layerName": "页脚链接-联系我们",
              "layerDescription": "页脚链接-联系我们",
              "style": {
                "fontSize": "14px",
                "color": "rgb(148,163,184)"
              },
              "text": "联系我们"
            },
            {
              "nid": 88,
              "tag": "span",
              "rect": {
                "x": 1080,
                "y": 1840,
                "w": 160,
                "h": 20
              },
              "layerType": "text",
              "layerName": "页脚链接-状态页面",
              "layerDescription": "页脚链接-状态页面",
              "style": {
                "fontSize": "14px",
                "color": "rgb(148,163,184)"
              },
              "text": "状态页面"
            },
            {
              "nid": 89,
              "tag": "span",
              "rect": {
                "x": 1080,
                "y": 1872,
                "w": 160,
                "h": 20
              },
              "layerType": "text",
              "layerName": "页脚链接-隐私政策",
              "layerDescription": "页脚链接-隐私政策",
              "style": {
                "fontSize": "14px",
                "color": "rgb(148,163,184)"
              },
              "text": "隐私政策"
            }
          ]
        },
        {
          "nid": 90,
          "tag": "hr",
          "rect": {
            "x": 120,
            "y": 1932,
            "w": 1200,
            "h": 1
          },
          "layerType": "frame",
          "layerName": "页脚分割线",
          "layerDescription": "页脚分割线",
          "style": {}
        },
        {
          "nid": 91,
          "tag": "span",
          "rect": {
            "x": 120,
            "y": 1952,
            "w": 500,
            "h": 20
          },
          "layerType": "text",
          "layerName": "版权文字",
          "layerDescription": "版权文字",
          "style": {
            "fontSize": "14px",
            "color": "rgb(100,116,139)"
          },
          "text": "© 2024 DesignHub. 保留所有权利。"
        },
        {
          "nid": 92,
          "tag": "span",
          "rect": {
            "x": 960,
            "y": 1952,
            "w": 80,
            "h": 20
          },
          "layerType": "text",
          "layerName": "页脚链接-隐私政策2",
          "layerDescription": "页脚链接-隐私政策2",
          "style": {
            "fontSize": "14px",
            "color": "rgb(100,116,139)"
          },
          "text": "隐私政策"
        },
        {
          "nid": 93,
          "tag": "span",
          "rect": {
            "x": 1064,
            "y": 1952,
            "w": 80,
            "h": 20
          },
          "layerType": "text",
          "layerName": "页脚链接-服务条款",
          "layerDescription": "页脚链接-服务条款",
          "style": {
            "fontSize": "14px",
            "color": "rgb(100,116,139)"
          },
          "text": "服务条款"
        },
        {
          "nid": 94,
          "tag": "span",
          "rect": {
            "x": 1168,
            "y": 1952,
            "w": 100,
            "h": 20
          },
          "layerType": "text",
          "layerName": "页脚链接-Cookie",
          "layerDescription": "页脚链接-Cookie",
          "style": {
            "fontSize": "14px",
            "color": "rgb(100,116,139)"
          },
          "text": "Cookie 设置"
        }
      ]
    }
  ]
}